indeed/__init__.py
indeed/functions.py
bergwerkapp-1.0.1.dist-info/LICENSE.txt
bergwerkapp-1.0.1.dist-info/METADATA
bergwerkapp-1.0.1.dist-info/WHEEL
bergwerkapp-1.0.1.dist-info/top_level.txt
bergwerkapp-1.0.1.dist-info/RECORD
